lfy/__init__.py
lfy/api/__init__.py
lfy/api/constant.py
lfy/api/server/__init__.py
lfy/api/server/ocr/__init__.py
lfy/api/server/ocr/baidu.py
lfy/api/server/ocr/easyocr.py
lfy/api/server/ocr/pytesseract.py
lfy/api/server/tra/__init__.py
lfy/api/server/tra/aliyun.py
lfy/api/server/tra/baidu.py
lfy/api/server/tra/bing.py
lfy/api/server/tra/com.py
lfy/api/server/tra/google.py
lfy/api/server/tra/huoshan.py
lfy/api/server/tra/tencent.py
lfy/qt/__init__.py
lfy/qt/lfy.py
lfy/qt/main.py
lfy/qt/preference.py
lfy/qt/translate.py
lfy/qt/tray.py
lfy/resources/cool.ldr.lfy.svg
lfy/resources/locale/it/LC_MESSAGES/cool.ldr.lfy.mo
lfy/resources/locale/zh_CN/LC_MESSAGES/cool.ldr.lfy.mo
lfy/utils/__init__.py
lfy/utils/bak.py
lfy/utils/check_update.py
lfy/utils/code.py
lfy/utils/debug.py
lfy/utils/settings.py
lfy-0.1.1.dist-info/LICENSE
lfy-0.1.1.dist-info/METADATA
lfy-0.1.1.dist-info/WHEEL
lfy-0.1.1.dist-info/entry_points.txt
lfy-0.1.1.dist-info/top_level.txt
lfy-0.1.1.dist-info/RECORD
