Metadata-Version: 2.1
Name: lfy
Version: 0.1.1
Summary: Translation software designed for reading scientific research literature.
Author-email: yuhldr <yuhldr@qq.com>
Project-URL: Homepage, https://github.com/ldrfy/lfy
Project-URL: Bug Tracker, https://github.com/ldrfy/lfy/issues
Classifier: Programming Language :: Python :: 3
Classifier: License :: OSI Approved :: GNU General Public License v3 (GPLv3)
Classifier: Operating System :: OS Independent
Requires-Python: >=3.8
License-File: LICENSE
Requires-Dist: requests
Requires-Dist: pillow
Requires-Dist: PyQt6
